Metadata-Version: 2.1
Name: aidp
Version: 0.0.1
Summary: AI Data Platform
Author: AI Data Platform Engineering Team
Author-email: aidp@sktai.io
Classifier: Programming Language :: Python :: 3
Classifier: License :: OSI Approved :: MIT License
Classifier: Operating System :: OS Independent
Requires-Python: >=3.11
